codehem/__init__.py
codehem/cli.py
codehem/main.py
codehem/core/__init__.py
codehem/core/ast_handler.py
codehem/core/languages.py
codehem/core/models.py
codehem/core/query_builder.py
codehem/core/caching/__init__.py
codehem/core/caching/cache_manager.py
codehem/core/finder/__init__.py
codehem/core/finder/base.py
codehem/core/finder/factory.py
codehem/core/finder/lang/__init__.py
codehem/core/finder/lang/python_code_finder.py
codehem/core/finder/lang/typescript_code_finder.py
codehem/core/formatting/__init__.py
codehem/core/formatting/formatter.py
codehem/core/formatting/python_formatter.py
codehem/core/formatting/typescript_formatter.py
codehem/core/manipulator/__init__.py
codehem/core/manipulator/abstract.py
codehem/core/manipulator/base.py
codehem/core/manipulator/factory.py
codehem/core/manipulator/lang/__init__.py
codehem/core/manipulator/lang/python_manipulator.py
codehem/core/manipulator/lang/typescript_manipulator.py
codehem/core/services/__init__.py
codehem/core/services/extraction_service.py
codehem/core/services/python_indentation_service.py
codehem/core/strategies/__init__.py
codehem/core/strategies/language_strategy.py
codehem/core/strategies/python_strategy.py
codehem/core/strategies/typescript_strategy.py
codehem/core/utils/__init__.py
codehem/core/utils/logs.py
codehem-0.1.6.1.dist-info/licenses/LICENSE
tests/__init__.py
tests/test_extract_code.py
tests/test_filter_method.py
tests/test_language_detection.py
tests/test_parser_robustness.py
tests/fixtures/__init__.py
tests/fixtures/python/__init__.py
tests/fixtures/python/class/__init__.py
tests/fixtures/python/class/class_missing.py
tests/fixtures/python/class/class_simple.py
tests/fixtures/python/class_methods/__init__.py
tests/fixtures/python/class_methods/class_method_indicator.py
tests/fixtures/python/class_methods/classes_from_code.py
tests/fixtures/python/class_methods/methods_from_class.py
tests/fixtures/python/code_style/__init__.py
tests/fixtures/python/code_style/blank_lines_code.py
tests/fixtures/python/code_style/commented_code.py
codehem-0.1.6.1.dist-info/METADATA
codehem-0.1.6.1.dist-info/WHEEL
codehem-0.1.6.1.dist-info/entry_points.txt
codehem-0.1.6.1.dist-info/top_level.txt
codehem-0.1.6.1.dist-info/RECORD
