Metadata-Version: 2.4
Name: CodeHem
Version: 0.1.6.1
Summary: A language-agnostic library for code querying and manipulation
Home-page: https://github.com/jacekjursza/CodeHem
Author: Jacek Jursza
Author-email: jacek.jursza@gmail.com
Classifier: Programming Language :: Python :: 3
Classifier: License :: OSI Approved :: MIT License
Classifier: Operating System :: OS Independent
Classifier: Development Status :: 4 - Beta
Classifier: Intended Audience :: Developers
Classifier: Topic :: Software Development :: Libraries :: Python Modules
Requires-Python: >=3.7
License-File: LICENSE
Requires-Dist: tree-sitter==0.24.0
Requires-Dist: tree-sitter-javascript==0.23.1
Requires-Dist: tree-sitter-python==0.23.6
Requires-Dist: tree-sitter-typescript==0.23.2
Requires-Dist: typing_extensions==4.12.2
Requires-Dist: rich==13.9.4
Requires-Dist: pydantic==2.10.6
Requires-Dist: pydantic_core==2.27.2
Requires-Dist: setuptools>=77.0.1
Provides-Extra: dev
Requires-Dist: pytest>=7.0.0; extra == "dev"
Requires-Dist: pytest-cov>=3.0.0; extra == "dev"
Requires-Dist: twine; extra == "dev"
Requires-Dist: build; extra == "dev"
Requires-Dist: wheel; extra == "dev"
Dynamic: author
Dynamic: author-email
Dynamic: classifier
Dynamic: description
Dynamic: description-content-type
Dynamic: home-page
Dynamic: license-file
Dynamic: provides-extra
Dynamic: requires-dist
Dynamic: requires-python
Dynamic: summary
